{
  "date": "2026-01-30",
  "total_stocks": 120,
  "results": [
    {
      "name": "SK증권",
      "code": "001510",
      "current_price": "833원",
      "change": "-57원",
      "change_percent": "-6.82%",
      "signal": "적극매도",
      "reason": "금일 장대 음봉과 급증한 거래량은 강력한 매도 압력을 시사하며, 모든 이동평균선을 하향 이탈했습니다. 외국인과 기관의 대규모 순매도가 관찰되어 추가 하락 가능성이 높습니다.",
      "capture_time": "2026-01-30 09:16:47",
      "analysis_time": "2026-01-30 09:34:23"
    },
    {
      "name": "남선알미늄",
      "code": "008350",
      "current_price": "1,295원",
      "change": "+55원",
      "change_percent": "+4.43%",
      "signal": "중립",
      "reason": "현재가가 5일, 20일 이동평균선을 상향 돌파하며 단기 반등 시그널이 보이지만, 거래량이 평균 수준이며 장기 이평선은 아직 하향 추세입니다. 외인/기관 순매도가 지속되고 있어 추세 전환을 확신하기는 어렵습니다.",
      "capture_time": "2026-01-30 09:16:55",
      "analysis_time": "2026-01-30 09:34:23"
    },
    {
      "name": "삼성전자",
      "code": "005930",
      "current_price": "161,500원",
      "change": "+5,700원",
      "change_percent": "+3.70%",
      "signal": "매수",
      "reason": "장기 이동평균선 위에 주가가 안정적으로 위치하고 있으며, 외국인과 기관의 순매수세가 긍정적입니다. 견조한 상승 추세 속에서 거래량 동반한 양봉은 추가 상승 기대를 높입니다.",
      "capture_time": "2026-01-30 09:17:02",
      "analysis_time": "2026-01-30 09:34:23"
    },
    {
      "name": "조일알미늄",
      "code": "018470",
      "current_price": "3,945원",
      "change": "+130원",
      "change_percent": "+3.41%",
      "signal": "중립",
      "reason": "현재 주가가 모든 이동평균선 위에 있지만, 최근 급등 후 조정 과정으로 보이며 거래량은 감소 추세입니다. 외국인과 기관의 혼조세가 관찰되어 명확한 방향성을 보이지 않습니다.",
      "capture_time": "2026-01-30 09:17:09",
      "analysis_time": "2026-01-30 09:34:23"
    },
    {
      "name": "대한전선",
      "code": "001440",
      "current_price": "30,150원",
      "change": "+1,900원",
      "change_percent": "+6.71%",
      "signal": "매수",
      "reason": "금일 상승과 함께 거래량이 급증하며 5일 및 20일 이동평균선을 상향 돌파했습니다. 외국인과 기관의 순매수가 두드러져 단기적인 상승 모멘텀이 강화될 것으로 보입니다.",
      "capture_time": "2026-01-30 09:17:16",
      "analysis_time": "2026-01-30 09:34:23"
    },
    {
      "name": "미래에셋증권",
      "code": "006800",
      "current_price": "42,000원",
      "change": "+1,200원",
      "change_percent": "+2.94%",
      "signal": "매수",
      "reason": "주가가 5일, 20일 이동평균선 위에 위치하며 상승 추세를 유지하고 있습니다. 외국인과 기관의 연속적인 순매수가 주가를 지지하며 추가 상승 여력이 있을 것으로 판단됩니다.",
      "capture_time": "2026-01-30 09:17:24",
      "analysis_time": "2026-01-30 09:34:23"
    },
    {
      "name": "대원전선",
      "code": "006340",
      "current_price": "3,945원",
      "change": "+130원",
      "change_percent": "+3.41%",
      "signal": "매수",
      "reason": "5일, 20일 이동평균선 위에 주가가 안착하며 상승 추세를 이어가고 있습니다. 외국인과 기관의 견조한 순매수세가 주가 상승에 긍정적인 영향을 미치고 있습니다.",
      "capture_time": "2026-01-30 09:17:31",
      "analysis_time": "2026-01-30 09:34:23"
    },
    {
      "name": "알루코",
      "code": "001780",
      "current_price": "2,840원",
      "change": "+50원",
      "change_percent": "+1.79%",
      "signal": "중립",
      "reason": "5일, 20일 이동평균선 부근에서 등락을 거듭하며 뚜렷한 추세가 없습니다. 외국인과 기관의 매매 동향이 혼조세를 보이고 있어 관망이 필요합니다.",
      "capture_time": "2026-01-30 09:17:38",
      "analysis_time": "2026-01-30 09:34:23"
    },
    {
      "name": "신성이엔지",
      "code": "011930",
      "current_price": "1,809원",
      "change": "+20원",
      "change_percent": "+1.11%",
      "signal": "중립",
      "reason": "주가가 5일 이동평균선 위에 있으나 장기 이동평균선 아래에 위치하며, 거래량은 평균 수준입니다. 투자자별 매매 동향도 명확한 방향성이 없어 추세 확인이 필요합니다.",
      "capture_time": "2026-01-30 09:17:45",
      "analysis_time": "2026-01-30 09:34:23"
    },
    {
      "name": "대창",
      "code": "012800",
      "current_price": "1,459원",
      "change": "+20원",
      "change_percent": "+1.39%",
      "signal": "중립",
      "reason": "주가가 이동평균선 사이에서 횡보하고 있으며, 거래량에 큰 변화가 없습니다. 외국인과 기관의 매매 동향도 뚜렷한 흐름을 보이지 않아 관망이 필요합니다.",
      "capture_time": "2026-01-30 09:17:52",
      "analysis_time": "2026-01-30 09:34:23"
    },
    {
      "name": "이구산업",
      "code": "025820",
      "current_price": "6,300원",
      "change": "+110원",
      "change_percent": "+1.78%",
      "signal": "중립",
      "reason": "단기 이동평균선 위에 위치하며 소폭 상승했으나, 거래량은 평균 수준입니다. 외국인과 기관의 매매 동향이 일관되지 않아 강한 매수 시그널로 보기 어렵습니다.",
      "capture_time": "2026-01-30 09:18:00",
      "analysis_time": "2026-01-30 09:34:23"
    },
    {
      "name": "한화투자증권",
      "code": "003530",
      "current_price": "6,650원",
      "change": "+40원",
      "change_percent": "+0.61%",
      "signal": "중립",
      "reason": "주가가 5일 이동평균선 부근에서 횡보하며 단기 상승 모멘텀이 약화된 모습입니다. 투자자별 매매도 혼조세라 확실한 방향성 없이 관망이 필요합니다.",
      "capture_time": "2026-01-30 09:18:07",
      "analysis_time": "2026-01-30 09:34:23"
    },
    {
      "name": "상상인증권",
      "code": "001290",
      "current_price": "732원",
      "change": "-48원",
      "change_percent": "-6.15%",
      "signal": "적극매도",
      "reason": "금일 대량 거래와 함께 장대 음봉이 출현하며 5일 이동평균선을 하향 이탈했습니다. 외국인과 기관의 대규모 순매도가 관찰되어 하락 추세 전환 가능성이 높습니다.",
      "capture_time": "2026-01-30 09:18:14",
      "analysis_time": "2026-01-30 09:34:23"
    },
    {
      "name": "윌비스",
      "code": "008600",
      "current_price": "345원",
      "change": "+10원",
      "change_percent": "+0.29%",
      "signal": "중립",
      "reason": "주가가 이동평균선 아래에서 횡보하며 약세 흐름을 보이고 있습니다. 거래량이 적고 투자자별 매매 동향도 뚜렷하지 않아 관망이 필요합니다.",
      "capture_time": "2026-01-30 09:18:21",
      "analysis_time": "2026-01-30 09:34:23"
    },
    {
      "name": "흥아해운",
      "code": "003280",
      "current_price": "1,738원",
      "change": "+10원",
      "change_percent": "+0.58%",
      "signal": "중립",
      "reason": "주가가 5일 이동평균선 위에 있으나 20일 이동평균선 저항을 받고 있습니다. 거래량은 평균 수준이며, 외국인과 기관의 혼조세로 추세 전환을 확신하기 어렵습니다.",
      "capture_time": "2026-01-30 09:18:28",
      "analysis_time": "2026-01-30 09:34:23"
    },
    {
      "name": "한국ANKOR유전",
      "code": "152550",
      "current_price": "216원",
      "change": "+1원",
      "change_percent": "+0.47%",
      "signal": "중립",
      "reason": "주가가 바닥권에서 횡보하며 큰 변동성을 보이지 않습니다. 거래량이 매우 적고, 투자자별 매매 동향도 뚜렷한 추세를 형성하지 못하고 있습니다.",
      "capture_time": "2026-01-30 09:18:35",
      "analysis_time": "2026-01-30 09:34:23"
    },
    {
      "name": "SK하이닉스",
      "code": "000660",
      "current_price": "894,000원",
      "change": "+33,000원",
      "change_percent": "+3.83%",
      "signal": "매수",
      "reason": "5일, 20일 이동평균선 위에서 안정적인 상승 추세를 유지하고 있으며, 외국인과 기관의 꾸준한 순매수세가 긍정적입니다. 견조한 실적 전망과 함께 추가 상승 가능성이 높습니다.",
      "capture_time": "2026-01-30 09:18:42",
      "analysis_time": "2026-01-30 09:34:23"
    },
    {
      "name": "삼성제약",
      "code": "001360",
      "current_price": "1,848원",
      "change": "+10원",
      "change_percent": "+0.54%",
      "signal": "중립",
      "reason": "주가가 5일 이동평균선 위에 위치하지만, 거래량이 적고 장기 이평선 아래에 있습니다. 외국인과 기관의 혼조세로 뚜렷한 상승 모멘텀을 찾기 어렵습니다.",
      "capture_time": "2026-01-30 09:18:50",
      "analysis_time": "2026-01-30 09:34:23"
    },
    {
      "name": "한화시스템",
      "code": "272210",
      "current_price": "97,400원",
      "change": "+4,500원",
      "change_percent": "+4.85%",
      "signal": "매수",
      "reason": "금일 거래량을 동반한 상승으로 5일, 20일 이동평균선을 상향 돌파하며 단기 추세가 강해졌습니다. 외국인과 기관의 순매수 전환이 긍정적인 신호로 보입니다.",
      "capture_time": "2026-01-30 09:18:58",
      "analysis_time": "2026-01-30 09:34:23"
    },
    {
      "name": "에이프로젠",
      "code": "007460",
      "current_price": "755원",
      "change": "+1원",
      "change_percent": "+0.13%",
      "signal": "중립",
      "reason": "주가가 5일 이동평균선 아래에서 횡보하며 약세 흐름을 보이고 있습니다. 거래량이 적고, 외국인과 기관의 매매 동향도 혼조세라 관망이 필요합니다.",
      "capture_time": "2026-01-30 09:19:05",
      "analysis_time": "2026-01-30 09:34:23"
    },
    {
      "name": "대덕전자",
      "code": "353200",
      "current_price": "60,000원",
      "change": "+7,500원",
      "change_percent": "+14.29%",
      "signal": "적극매수",
      "reason": "대량 거래를 동반한 장대 양봉으로 모든 이동평균선을 강하게 돌파하며 강력한 상승 추세를 시작했습니다. 외국인과 기관의 대규모 동반 순매수가 확인되어 추가 상승 기대가 매우 높습니다.",
      "capture_time": "2026-01-30 09:19:13",
      "analysis_time": "2026-01-30 09:34:23"
    },
    {
      "name": "다이나믹디자인",
      "code": "145210",
      "current_price": "4,300원",
      "change": "+37원",
      "change_percent": "+0.87%",
      "signal": "중립",
      "reason": "주가가 이동평균선 아래에서 횡보하며 약세 흐름을 보이고 있습니다. 거래량이 적고 수급도 명확하지 않아 추가적인 관망이 필요합니다.",
      "capture_time": "2026-01-30 09:19:20",
      "analysis_time": "2026-01-30 09:34:23"
    },
    {
      "name": "유진투자증권",
      "code": "001200",
      "current_price": "4,270원",
      "change": "+30원",
      "change_percent": "+0.70%",
      "signal": "매수",
      "reason": "주가가 5일 이동평균선 위에 위치하며 양호한 상승 추세를 보이고 있습니다. 외국인의 꾸준한 순매수세가 긍정적이며 추가 상승 여력이 있을 것으로 판단됩니다.",
      "capture_time": "2026-01-30 09:19:27",
      "analysis_time": "2026-01-30 09:34:23"
    },
    {
      "name": "KG모빌리티",
      "code": "003620",
      "current_price": "3,845원",
      "change": "-35원",
      "change_percent": "-0.90%",
      "signal": "중립",
      "reason": "주가가 이동평균선 사이에서 횡보하며 방향성을 잃은 모습입니다. 거래량이 적고 외국인과 기관의 매매 동향도 혼조세라 관망이 필요합니다.",
      "capture_time": "2026-01-30 09:19:35",
      "analysis_time": "2026-01-30 09:34:23"
    },
    {
      "name": "한온시스템",
      "code": "018880",
      "current_price": "3,325원",
      "change": "+20원",
      "change_percent": "+0.16%",
      "signal": "중립",
      "reason": "주가가 이동평균선 아래에서 횡보하며 약세 흐름을 보이고 있습니다. 거래량이 적고 투자자별 매매 동향도 뚜렷하지 않아 관망이 필요합니다.",
      "capture_time": "2026-01-30 09:19:42",
      "analysis_time": "2026-01-30 09:34:23"
    },
    {
      "name": "두산에너빌리티",
      "code": "034020",
      "current_price": "92,500원",
      "change": "+1,600원",
      "change_percent": "+1.76%",
      "signal": "매수",
      "reason": "주가가 5일 이동평균선 위에 위치하며 단기 상승 추세를 유지하고 있습니다. 외국인의 연속적인 순매수가 주가 상승에 긍정적인 영향을 미치고 있습니다.",
      "capture_time": "2026-01-30 09:19:50",
      "analysis_time": "2026-01-30 09:34:23"
    },
    {
      "name": "대한해운",
      "code": "005880",
      "current_price": "1,995원",
      "change": "-5원",
      "change_percent": "-0.99%",
      "signal": "중립",
      "reason": "주가가 5일 이동평균선 아래에서 횡보하며 단기 약세 흐름을 보입니다. 외국인과 기관의 매매 동향이 혼조세라 추가적인 관망이 필요합니다.",
      "capture_time": "2026-01-30 09:19:58",
      "analysis_time": "2026-01-30 09:34:23"
    },
    {
      "name": "한농화성",
      "code": "011500",
      "current_price": "27,650원",
      "change": "+1,850원",
      "change_percent": "+7.18%",
      "signal": "매수",
      "reason": "금일 거래량을 동반한 상승으로 5일, 20일 이동평균선을 상향 돌파하며 강한 상승 모멘텀을 보입니다. 외국인과 기관의 순매수가 확인되어 추가 상승 기대가 있습니다.",
      "capture_time": "2026-01-30 09:20:05",
      "analysis_time": "2026-01-30 09:34:23"
    },
    {
      "name": "삼성전자우",
      "code": "005935",
      "current_price": "115,700원",
      "change": "0원",
      "change_percent": "0.00%",
      "signal": "중립",
      "reason": "현재 가격은 변동 없이 5일 이동평균선 위에 위치하고 있으나, 외국인 순매도와 기관 순매수가 엇갈려 명확한 방향성이 보이지 않습니다. 관망하며 추세 확인이 필요합니다.",
      "capture_time": "2026-01-30 09:20:13",
      "analysis_time": "2026-01-30 09:34:23"
    },
    {
      "name": "SK텔레콤",
      "code": "017670",
      "current_price": "73,200원",
      "change": "+200원",
      "change_percent": "+0.27%",
      "signal": "중립",
      "reason": "주가가 5일 이동평균선 부근에서 횡보하며 상승 탄력이 둔화된 모습입니다. 외국인과 기관의 매매 동향이 혼조세를 보여 추세 확인이 필요합니다.",
      "capture_time": "2026-01-30 09:20:21",
      "analysis_time": "2026-01-30 09:34:23"
    },
    {
      "name": "서원",
      "code": "021050",
      "current_price": "1,330원",
      "change": "+30원",
      "change_percent": "+2.31%",
      "signal": "매수",
      "reason": "주가가 5일, 20일 이동평균선을 상향 돌파하며 단기 상승 추세로 전환하는 모습입니다. 외국인과 기관의 동반 순매수가 긍정적인 신호로 판단됩니다.",
      "capture_time": "2026-01-30 09:20:28",
      "analysis_time": "2026-01-30 09:34:23"
    },
    {
      "name": "현대차",
      "code": "005380",
      "current_price": "509,000원",
      "change": "+20,000원",
      "change_percent": "+3.93%",
      "signal": "매수",
      "reason": "주가가 모든 이동평균선 위에 위치하며 견고한 상승 추세를 보이고 있습니다. 외국인의 대규모 순매수가 지속되어 추가 상승 여력이 있을 것으로 판단됩니다.",
      "capture_time": "2026-01-30 09:20:36",
      "analysis_time": "2026-01-30 09:34:23"
    },
    {
      "name": "한화갤러리아",
      "code": "452260",
      "current_price": "1,858원",
      "change": "+10원",
      "change_percent": "+0.54%",
      "signal": "중립",
      "reason": "주가가 5일 이동평균선 아래에서 횡보하며 약세 흐름을 보입니다. 거래량이 적고 외국인과 기관의 매매 동향도 혼조세라 관망이 필요합니다.",
      "capture_time": "2026-01-30 09:20:43",
      "analysis_time": "2026-01-30 09:34:23"
    },
    {
      "name": "와이투솔루션",
      "code": "011690",
      "current_price": "5,790원",
      "change": "+180원",
      "change_percent": "+3.21%",
      "signal": "중립",
      "reason": "주가가 이동평균선 부근에서 등락을 거듭하며 뚜렷한 방향성을 찾지 못하고 있습니다. 거래량이 적고 외국인과 기관의 매매 동향도 혼조세입니다.",
      "capture_time": "2026-01-30 09:20:50",
      "analysis_time": "2026-01-30 09:34:23"
    },
    {
      "name": "한화생명",
      "code": "088350",
      "current_price": "3,505원",
      "change": "-60원",
      "change_percent": "-1.68%",
      "signal": "중립",
      "reason": "주가가 5일 이동평균선을 하향 이탈하며 단기 하락 추세로 전환될 가능성이 있습니다. 외국인과 기관의 매매 동향이 혼조세로 관망이 필요합니다.",
      "capture_time": "2026-01-30 09:20:58",
      "analysis_time": "2026-01-30 09:34:23"
    },
    {
      "name": "대우건설",
      "code": "047040",
      "current_price": "4,985원",
      "change": "+165원",
      "change_percent": "+3.30%",
      "signal": "매수",
      "reason": "금일 상승으로 5일, 20일 이동평균선을 상향 돌파하며 단기 상승 추세로 전환될 가능성이 높습니다. 외국인과 기관의 순매수세가 긍정적입니다.",
      "capture_time": "2026-01-30 09:21:06",
      "analysis_time": "2026-01-30 09:34:23"
    },
    {
      "name": "삼성중공업",
      "code": "010140",
      "current_price": "29,700원",
      "change": "+1,130원",
      "change_percent": "+3.95%",
      "signal": "매수",
      "reason": "5일 이동평균선 위에 주가가 위치하며 상승 추세를 유지하고 있으며, 외국인과 기관의 순매수세가 긍정적입니다. 견조한 흐름 속에서 추가 상승 여력이 있을 것으로 판단됩니다.",
      "capture_time": "2026-01-30 09:21:14",
      "analysis_time": "2026-01-30 09:34:23"
    },
    {
      "name": "한국전력",
      "code": "015760",
      "current_price": "59,900원",
      "change": "+1,200원",
      "change_percent": "+1.97%",
      "signal": "매수",
      "reason": "주가가 5일, 20일 이동평균선 위에 위치하며 안정적인 상승 흐름을 보이고 있습니다. 외국인의 연속적인 순매수세가 주가 상승에 긍정적인 영향을 미치고 있습니다.",
      "capture_time": "2026-01-30 09:21:21",
      "analysis_time": "2026-01-30 09:34:23"
    },
    {
      "name": "한화비전",
      "code": "489790",
      "current_price": "57,500원",
      "change": "+2,100원",
      "change_percent": "+3.79%",
      "signal": "매수",
      "reason": "금일 거래량을 동반한 상승으로 5일, 20일 이동평균선을 상향 돌파하며 단기 추세가 강해졌습니다. 외국인과 기관의 순매수세가 긍정적입니다.",
      "capture_time": "2026-01-30 09:21:29",
      "analysis_time": "2026-01-30 09:34:23"
    },
    {
      "name": "미래에셋증권우",
      "code": "006805",
      "current_price": "18,450원",
      "change": "+160원",
      "change_percent": "+0.90%",
      "signal": "중립",
      "reason": "주가가 5일 이동평균선 위에 있으나 장기 이동평균선 아래에 위치하며 방향성이 모호합니다. 외국인과 기관의 매매 동향이 혼조세라 추가적인 관망이 필요합니다.",
      "capture_time": "2026-01-30 09:21:37",
      "analysis_time": "2026-01-30 09:34:23"
    },
    {
      "name": "유안타증권",
      "code": "003470",
      "current_price": "4,555원",
      "change": "+15원",
      "change_percent": "+0.33%",
      "signal": "중립",
      "reason": "주가가 이동평균선 부근에서 횡보하며 뚜렷한 추세가 없습니다. 외국인과 기관의 매매 동향도 혼조세를 보이고 있어 관망이 필요합니다.",
      "capture_time": "2026-01-30 09:21:45",
      "analysis_time": "2026-01-30 09:34:23"
    },
    {
      "name": "팬오션",
      "code": "028670",
      "current_price": "4,695원",
      "change": "+115원",
      "change_percent": "+2.39%",
      "signal": "매수",
      "reason": "금일 거래량을 동반한 상승으로 5일 이동평균선을 상향 돌파하며 단기 상승 추세로 전환될 가능성이 높습니다. 외국인과 기관의 동반 순매수가 긍정적입니다.",
      "capture_time": "2026-01-30 09:21:52",
      "analysis_time": "2026-01-30 09:34:23"
    },
    {
      "name": "삼영",
      "code": "003720",
      "current_price": "6,150원",
      "change": "+70원",
      "change_percent": "+1.15%",
      "signal": "중립",
      "reason": "주가가 이동평균선 부근에서 횡보하며 뚜렷한 추세가 없습니다. 외국인과 기관의 매매 동향이 혼조세를 보이고 있어 관망이 필요합니다.",
      "capture_time": "2026-01-30 09:22:00",
      "analysis_time": "2026-01-30 09:34:23"
    },
    {
      "name": "한솔홈데코",
      "code": "029750",
      "current_price": "611원",
      "change": "+10원",
      "change_percent": "+1.66%",
      "signal": "중립",
      "reason": "주가가 이동평균선 아래에서 횡보하며 약세 흐름을 보입니다. 거래량이 적고 외국인과 기관의 매매 동향도 혼조세라 관망이 필요합니다.",
      "capture_time": "N/A",
      "analysis_time": "2026-01-30 09:34:23"
    },
    {
      "name": "삼일제약",
      "code": "000520",
      "current_price": "10,040원",
      "change": "-330원",
      "change_percent": "-3.19%",
      "signal": "매도",
      "reason": "금일 음봉과 함께 5일 이동평균선을 하향 이탈하며 단기 하락 추세로 전환될 가능성이 높습니다. 외국인과 기관의 순매도 전환이 부정적인 신호로 판단됩니다.",
      "capture_time": "2026-01-30 09:22:15",
      "analysis_time": "2026-01-30 09:34:23"
    },
    {
      "name": "카카오",
      "code": "035720",
      "current_price": "62,600원",
      "change": "+2,500원",
      "change_percent": "+4.16%",
      "signal": "매수",
      "reason": "금일 상승으로 5일, 20일 이동평균선을 상향 돌파하며 단기 상승 추세로 전환될 가능성이 높습니다. 외국인과 기관의 동반 순매수가 긍정적인 신호로 판단됩니다.",
      "capture_time": "2026-01-30 09:22:23",
      "analysis_time": "2026-01-30 09:34:23"
    },
    {
      "name": "삼화전기",
      "code": "009470",
      "current_price": "54,800원",
      "change": "+1,000원",
      "change_percent": "+1.86%",
      "signal": "매수",
      "reason": "주가가 5일 이동평균선 위에 위치하며 상승 추세를 유지하고 있습니다. 외국인과 기관의 꾸준한 순매수세가 주가 상승에 긍정적인 영향을 미치고 있습니다.",
      "capture_time": "2026-01-30 09:22:31",
      "analysis_time": "2026-01-30 09:34:23"
    },
    {
      "name": "보락",
      "code": "002760",
      "current_price": "1,246원",
      "change": "+20원",
      "change_percent": "+1.63%",
      "signal": "중립",
      "reason": "주가가 이동평균선 부근에서 횡보하며 뚜렷한 추세가 없습니다. 거래량이 적고 외국인과 기관의 매매 동향도 혼조세를 보이고 있어 관망이 필요합니다.",
      "capture_time": "2026-01-30 09:22:39",
      "analysis_time": "2026-01-30 09:34:23"
    },
    {
      "name": "한국석유",
      "code": "004090",
      "current_price": "15,390원",
      "change": "+30원",
      "change_percent": "+0.20%",
      "signal": "중립",
      "reason": "주가가 이동평균선 아래에서 횡보하며 약세 흐름을 보입니다. 거래량이 적고 외국인과 기관의 매매 동향도 뚜렷하지 않아 관망이 필요합니다.",
      "capture_time": "2026-01-30 09:22:46",
      "analysis_time": "2026-01-30 09:34:23"
    },
    {
      "name": "퍼스텍",
      "code": "010820",
      "current_price": "4,165원",
      "change": "+35원",
      "change_percent": "+0.78%",
      "signal": "중립",
      "reason": "주가가 5일 이동평균선 아래에서 횡보하며 단기 약세 흐름을 보입니다. 외국인과 기관의 매매 동향이 혼조세로 추가적인 관망이 필요합니다.",
      "capture_time": "2026-01-30 09:22:54",
      "analysis_time": "2026-01-30 09:34:23"
    },
    {
      "name": "아주IB투자",
      "code": "027360",
      "current_price": "4,735원",
      "change": "+225원",
      "change_percent": "+4.99%",
      "signal": "매수",
      "reason": "금일 상승과 함께 거래량이 급증하며 5일 이동평균선을 상향 돌파했습니다. 외국인의 순매수세가 긍정적이며 추가 상승 모멘텀이 강화될 것으로 보입니다.",
      "capture_time": "2026-01-30 09:23:01",
      "analysis_time": "2026-01-30 09:34:23"
    },
    {
      "name": "네오펙트",
      "code": "290660",
      "current_price": "951원",
      "change": "-170원",
      "change_percent": "-15.17%",
      "signal": "적극매도",
      "reason": "금일 급락과 함께 대량 거래가 발생하며 모든 이동평균선을 강하게 하향 이탈했습니다. 외국인과 기관의 대규모 순매도가 관찰되어 강력한 매도 시그널로 판단됩니다.",
      "capture_time": "2026-01-30 09:23:08",
      "analysis_time": "2026-01-30 09:34:23"
    },
    {
      "name": "덕양에너젠",
      "code": "0001A0",
      "current_price": "25,450원",
      "change": "10,000원",
      "change_percent": "0.00%",
      "signal": "중립",
      "reason": "주식 거래가 발생하지 않아 가격 변동이 없으며, 차트나 매매 동향 데이터가 부재하여 분석이 어렵습니다. 관망하는 것이 현명합니다.",
      "capture_time": "2026-01-30 09:23:14",
      "analysis_time": "2026-01-30 09:34:23"
    },
    {
      "name": "흥국에프엔비",
      "code": "189980",
      "current_price": "2,475원",
      "change": "+60원",
      "change_percent": "+2.48%",
      "signal": "중립",
      "reason": "주가가 5일 이동평균선 위에 있으나 장기 이동평균선 아래에 위치하며 방향성이 모호합니다. 외국인과 기관의 매매 동향이 혼조세라 추가적인 관망이 필요합니다.",
      "capture_time": "2026-01-30 09:23:21",
      "analysis_time": "2026-01-30 09:34:23"
    },
    {
      "name": "신라젠",
      "code": "215600",
      "current_price": "4,290원",
      "change": "-685원",
      "change_percent": "-13.77%",
      "signal": "적극매도",
      "reason": "금일 급락과 함께 대량 거래가 발생하며 5일 이동평균선을 강하게 하향 이탈했습니다. 외국인과 기관의 대규모 순매도가 관찰되어 강력한 매도 시그널로 판단됩니다.",
      "capture_time": "2026-01-30 09:23:28",
      "analysis_time": "2026-01-30 09:34:23"
    },
    {
      "name": "재영솔루텍",
      "code": "049630",
      "current_price": "4,920원",
      "change": "+20원",
      "change_percent": "+0.40%",
      "signal": "중립",
      "reason": "주가가 5일 이동평균선 아래에서 횡보하며 약세 흐름을 보입니다. 거래량이 적고 외국인과 기관의 매매 동향도 뚜렷하지 않아 관망이 필요합니다.",
      "capture_time": "2026-01-30 09:23:35",
      "analysis_time": "2026-01-30 09:34:23"
    },
    {
      "name": "대한광통신",
      "code": "010170",
      "current_price": "3,870원",
      "change": "+45원",
      "change_percent": "+1.17%",
      "signal": "중립",
      "reason": "주가가 이동평균선 사이에서 횡보하며 뚜렷한 추세가 없습니다. 외국인과 기관의 매매 동향도 혼조세를 보이고 있어 관망이 필요합니다.",
      "capture_time": "2026-01-30 09:23:42",
      "analysis_time": "2026-01-30 09:34:23"
    },
    {
      "name": "링크드",
      "code": "193250",
      "current_price": "514원",
      "change": "+51원",
      "change_percent": "+11.02%",
      "signal": "매수",
      "reason": "금일 거래량이 급증하며 5일 이동평균선을 상향 돌파했습니다. 외국인의 순매수세가 긍정적이며 단기 반등 모멘텀이 강화될 것으로 보입니다.",
      "capture_time": "2026-01-30 09:23:49",
      "analysis_time": "2026-01-30 09:34:23"
    },
    {
      "name": "성우전자",
      "code": "081580",
      "current_price": "2,955원",
      "change": "+580원",
      "change_percent": "+24.42%",
      "signal": "적극매수",
      "reason": "금일 대량 거래와 함께 장대 양봉이 출현하며 모든 이동평균선을 강하게 돌파했습니다. 외국인과 기관의 강한 순매수 전환이 확인되어 강력한 매수 시그널로 판단됩니다.",
      "capture_time": "2026-01-30 09:23:56",
      "analysis_time": "2026-01-30 09:34:23"
    },
    {
      "name": "빛과전자",
      "code": "069540",
      "current_price": "1,718원",
      "change": "+40원",
      "change_percent": "+2.38%",
      "signal": "중립",
      "reason": "주가가 이동평균선 부근에서 등락을 거듭하며 뚜렷한 추세가 없습니다. 외국인과 기관의 매매 동향이 혼조세를 보이고 있어 관망이 필요합니다.",
      "capture_time": "2026-01-30 09:24:03",
      "analysis_time": "2026-01-30 09:34:23"
    },
    {
      "name": "휴림로봇",
      "code": "090710",
      "current_price": "15,040원",
      "change": "+420원",
      "change_percent": "+2.87%",
      "signal": "중립",
      "reason": "주가가 5일 이동평균선 아래에서 횡보하며 단기 약세 흐름을 보입니다. 외국인과 기관의 매매 동향이 혼조세로 추가적인 관망이 필요합니다.",
      "capture_time": "2026-01-30 09:24:10",
      "analysis_time": "2026-01-30 09:34:23"
    },
    {
      "name": "이미지스",
      "code": "115610",
      "current_price": "1,922원",
      "change": "+20원",
      "change_percent": "+1.05%",
      "signal": "중립",
      "reason": "주가가 이동평균선 아래에서 횡보하며 약세 흐름을 보입니다. 거래량이 적고 외국인과 기관의 매매 동향도 뚜렷하지 않아 관망이 필요합니다.",
      "capture_time": "2026-01-30 09:24:17",
      "analysis_time": "2026-01-30 09:34:23"
    },
    {
      "name": "우리기술",
      "code": "032820",
      "current_price": "8,960원",
      "change": "0원",
      "change_percent": "0.00%",
      "signal": "중립",
      "reason": "주식 거래가 발생하지 않아 가격 변동이 없으며, 차트나 매매 동향 데이터가 부재하여 분석이 어렵습니다. 관망하는 것이 현명합니다.",
      "capture_time": "2026-01-30 09:24:24",
      "analysis_time": "2026-01-30 09:34:23"
    },
    {
      "name": "에이비프로바이오",
      "code": "195990",
      "current_price": "199원",
      "change": "-30원",
      "change_percent": "-13.04%",
      "signal": "적극매도",
      "reason": "금일 급락과 함께 거래량이 급증하며 모든 이동평균선을 강하게 하향 이탈했습니다. 외국인의 대규모 순매도가 관찰되어 강력한 매도 시그널로 판단됩니다.",
      "capture_time": "2026-01-30 09:24:31",
      "analysis_time": "2026-01-30 09:34:23"
    },
    {
      "name": "삼표시멘트",
      "code": "038500",
      "current_price": "7,030원",
      "change": "+20원",
      "change_percent": "+0.28%",
      "signal": "중립",
      "reason": "주가가 이동평균선 아래에서 횡보하며 약세 흐름을 보입니다. 거래량이 적고 외국인과 기관의 매매 동향도 뚜렷하지 않아 관망이 필요합니다.",
      "capture_time": "2026-01-30 09:24:38",
      "analysis_time": "2026-01-30 09:34:23"
    },
    {
      "name": "아이언디바이스",
      "code": "464500",
      "current_price": "4,810원",
      "change": "+5원",
      "change_percent": "+0.10%",
      "signal": "중립",
      "reason": "주가가 이동평균선 아래에서 횡보하며 약세 흐름을 보입니다. 거래량이 적고 외국인과 기관의 매매 동향도 뚜렷하지 않아 관망이 필요합니다.",
      "capture_time": "2026-01-30 09:24:46",
      "analysis_time": "2026-01-30 09:34:23"
    },
    {
      "name": "조이시티",
      "code": "067000",
      "current_price": "3,125원",
      "change": "+10원",
      "change_percent": "+0.32%",
      "signal": "중립",
      "reason": "주가가 이동평균선 부근에서 횡보하며 뚜렷한 추세가 없습니다. 외국인과 기관의 매매 동향이 혼조세를 보이고 있어 관망이 필요합니다.",
      "capture_time": "2026-01-30 09:24:53",
      "analysis_time": "2026-01-30 09:34:23"
    },
    {
      "name": "와이즈버즈",
      "code": "273060",
      "current_price": "1,278원",
      "change": "+134원",
      "change_percent": "+11.71%",
      "signal": "매수",
      "reason": "금일 거래량이 급증하며 장대 양봉으로 5일, 20일 이동평균선을 상향 돌파했습니다. 외국인의 순매수세가 긍정적이며 단기 상승 모멘텀이 강화될 것으로 보입니다.",
      "capture_time": "2026-01-30 09:25:00",
      "analysis_time": "2026-01-30 09:34:23"
    },
    {
      "name": "인콘",
      "code": "083640",
      "current_price": "299원",
      "change": "-16원",
      "change_percent": "-5.08%",
      "signal": "적극매도",
      "reason": "금일 급락과 함께 대량 거래가 발생하며 5일 이동평균선을 강하게 하향 이탈했습니다. 외국인의 대규모 순매도가 관찰되어 강력한 매도 시그널로 판단됩니다.",
      "capture_time": "2026-01-30 09:25:07",
      "analysis_time": "2026-01-30 09:34:23"
    },
    {
      "name": "엔에이치스팩30호",
      "code": "466910",
      "current_price": "3,550원",
      "change": "+50원",
      "change_percent": "+1.42%",
      "signal": "중립",
      "reason": "주가가 이동평균선 아래에서 횡보하며 약세 흐름을 보입니다. 거래량이 적고 외국인과 기관의 매매 동향도 뚜렷하지 않아 관망이 필요합니다.",
      "capture_time": "2026-01-30 09:25:13",
      "analysis_time": "2026-01-30 09:34:23"
    },
    {
      "name": "한라캐스트",
      "code": "125490",
      "current_price": "2,100원",
      "change": "+20원",
      "change_percent": "+0.96%",
      "signal": "중립",
      "reason": "주가가 이동평균선 아래에서 횡보하며 약세 흐름을 보입니다. 거래량이 적고 외국인과 기관의 매매 동향도 뚜렷하지 않아 관망이 필요합니다.",
      "capture_time": "2026-01-30 09:25:20",
      "analysis_time": "2026-01-30 09:34:23"
    },
    {
      "name": "유일에너테크",
      "code": "340930",
      "current_price": "1,507원",
      "change": "-43원",
      "change_percent": "-2.77%",
      "signal": "매도",
      "reason": "주가가 5일 이동평균선을 하향 이탈하며 단기 하락 추세로 전환될 가능성이 높습니다. 외국인과 기관의 순매도세가 관찰되어 부정적인 신호로 판단됩니다.",
      "capture_time": "2026-01-30 09:25:27",
      "analysis_time": "2026-01-30 09:34:23"
    },
    {
      "name": "엠투엔",
      "code": "033310",
      "current_price": "2,100원",
      "change": "-180원",
      "change_percent": "-7.89%",
      "signal": "적극매도",
      "reason": "금일 급락과 함께 대량 거래가 발생하며 5일 이동평균선을 강하게 하향 이탈했습니다. 외국인과 기관의 대규모 순매도가 관찰되어 강력한 매도 시그널로 판단됩니다.",
      "capture_time": "2026-01-30 09:25:34",
      "analysis_time": "2026-01-30 09:34:23"
    },
    {
      "name": "SFA반도체",
      "code": "036540",
      "current_price": "7,220원",
      "change": "+360원",
      "change_percent": "+5.26%",
      "signal": "매수",
      "reason": "금일 거래량을 동반한 상승으로 5일, 20일 이동평균선을 상향 돌파하며 단기 상승 추세로 전환될 가능성이 높습니다. 외국인과 기관의 순매수 전환이 긍정적인 신호로 보입니다.",
      "capture_time": "2026-01-30 09:25:42",
      "analysis_time": "2026-01-30 09:34:23"
    },
    {
      "name": "보성파워텍",
      "code": "006910",
      "current_price": "8,060원",
      "change": "+70원",
      "change_percent": "+0.87%",
      "signal": "중립",
      "reason": "주가가 5일 이동평균선 아래에서 횡보하며 단기 약세 흐름을 보입니다. 외국인과 기관의 매매 동향이 혼조세로 추가적인 관망이 필요합니다.",
      "capture_time": "2026-01-30 09:25:48",
      "analysis_time": "2026-01-30 09:34:23"
    },
    {
      "name": "PS일렉트로닉스",
      "code": "332570",
      "current_price": "7,990원",
      "change": "0원",
      "change_percent": "0.00%",
      "signal": "중립",
      "reason": "주식 거래가 발생하지 않아 가격 변동이 없으며, 차트나 매매 동향 데이터가 부재하여 분석이 어렵습니다. 관망하는 것이 현명합니다.",
      "capture_time": "2026-01-30 09:25:56",
      "analysis_time": "2026-01-30 09:34:23"
    },
    {
      "name": "다날",
      "code": "064260",
      "current_price": "9,230원",
      "change": "-90원",
      "change_percent": "-0.97%",
      "signal": "중립",
      "reason": "주가가 5일 이동평균선 아래에서 횡보하며 단기 약세 흐름을 보입니다. 외국인과 기관의 매매 동향이 혼조세로 추가적인 관망이 필요합니다.",
      "capture_time": "2026-01-30 09:26:03",
      "analysis_time": "2026-01-30 09:34:23"
    },
    {
      "name": "에이비엘바이오",
      "code": "298380",
      "current_price": "202,500원",
      "change": "-43,500원",
      "change_percent": "-17.72%",
      "signal": "적극매도",
      "reason": "금일 급락과 함께 대량 거래가 발생하며 모든 이동평균선을 강하게 하향 이탈했습니다. 외국인과 기관의 대규모 동반 순매도가 관찰되어 강력한 매도 시그널로 판단됩니다.",
      "capture_time": "2026-01-30 09:26:10",
      "analysis_time": "2026-01-30 09:34:23"
    },
    {
      "name": "흥구석유",
      "code": "024060",
      "current_price": "14,790원",
      "change": "+660원",
      "change_percent": "+4.67%",
      "signal": "매수",
      "reason": "금일 거래량을 동반한 상승으로 5일, 20일 이동평균선을 상향 돌파하며 단기 상승 추세로 전환될 가능성이 높습니다. 외국인과 기관의 순매수세가 긍정적입니다.",
      "capture_time": "2026-01-30 09:26:17",
      "analysis_time": "2026-01-30 09:34:23"
    },
    {
      "name": "알파AI",
      "code": "043100",
      "current_price": "2,335원",
      "change": "+165원",
      "change_percent": "+7.60%",
      "signal": "매수",
      "reason": "금일 거래량을 동반한 상승으로 5일, 20일 이동평균선을 상향 돌파하며 단기 상승 추세로 전환될 가능성이 높습니다. 외국인과 기관의 순매수 전환이 긍정적입니다.",
      "capture_time": "2026-01-30 09:26:25",
      "analysis_time": "2026-01-30 09:34:23"
    },
    {
      "name": "덕산하이메탈",
      "code": "077360",
      "current_price": "9,280원",
      "change": "+850원",
      "change_percent": "+10.07%",
      "signal": "매수",
      "reason": "금일 대량 거래와 함께 장대 양봉이 출현하며 5일, 20일 이동평균선을 상향 돌파했습니다. 외국인과 기관의 동반 순매수가 확인되어 추가 상승 모멘텀이 강화될 것으로 보입니다.",
      "capture_time": "2026-01-30 09:26:32",
      "analysis_time": "2026-01-30 09:34:23"
    },
    {
      "name": "라온로보틱스",
      "code": "232680",
      "current_price": "20,000원",
      "change": "+1,140원",
      "change_percent": "+6.04%",
      "signal": "매수",
      "reason": "금일 거래량을 동반한 상승으로 5일, 20일 이동평균선을 상향 돌파하며 단기 상승 추세로 전환될 가능성이 높습니다. 외국인과 기관의 동반 순매수가 긍정적입니다.",
      "capture_time": "2026-01-30 09:26:39",
      "analysis_time": "2026-01-30 09:34:23"
    },
    {
      "name": "현대무벡스",
      "code": "319400",
      "current_price": "32,650원",
      "change": "0원",
      "change_percent": "0.00%",
      "signal": "중립",
      "reason": "주식 거래가 발생하지 않아 가격 변동이 없으며, 차트나 매매 동향 데이터가 부재하여 분석이 어렵습니다. 관망하는 것이 현명합니다.",
      "capture_time": "2026-01-30 09:26:46",
      "analysis_time": "2026-01-30 09:34:23"
    },
    {
      "name": "쎄노텍",
      "code": "222420",
      "current_price": "1,663원",
      "change": "+80원",
      "change_percent": "+4.59%",
      "signal": "매수",
      "reason": "금일 거래량 증가와 함께 양봉으로 5일, 20일 이동평균선을 상향 돌파하며 단기 상승 추세로 전환될 가능성이 높습니다. 외국인과 기관의 순매수 전환이 긍정적입니다.",
      "capture_time": "2026-01-30 09:26:53",
      "analysis_time": "2026-01-30 09:34:23"
    },
    {
      "name": "제주반도체",
      "code": "080220",
      "current_price": "37,250원",
      "change": "+450원",
      "change_percent": "+1.22%",
      "signal": "매수",
      "reason": "주가가 5일, 20일 이동평균선 위에 위치하며 상승 추세를 유지하고 있습니다. 외국인과 기관의 꾸준한 순매수세가 주가 상승에 긍정적인 영향을 미치고 있습니다.",
      "capture_time": "2026-01-30 09:27:01",
      "analysis_time": "2026-01-30 09:34:23"
    },
    {
      "name": "해성옵틱스",
      "code": "076610",
      "current_price": "1,472원",
      "change": "-87원",
      "change_percent": "-5.58%",
      "signal": "매도",
      "reason": "금일 음봉과 함께 5일, 20일 이동평균선을 하향 이탈하며 단기 하락 추세로 전환될 가능성이 높습니다. 외국인과 기관의 순매도 전환이 부정적인 신호로 판단됩니다.",
      "capture_time": "2026-01-30 09:27:07",
      "analysis_time": "2026-01-30 09:34:23"
    },
    {
      "name": "세아메카닉스",
      "code": "396300",
      "current_price": "4,195원",
      "change": "-40원",
      "change_percent": "-0.95%",
      "signal": "중립",
      "reason": "주가가 5일 이동평균선 아래에서 횡보하며 단기 약세 흐름을 보입니다. 외국인과 기관의 매매 동향이 혼조세로 추가적인 관망이 필요합니다.",
      "capture_time": "2026-01-30 09:27:14",
      "analysis_time": "2026-01-30 09:34:23"
    },
    {
      "name": "아이톡시",
      "code": "052770",
      "current_price": "1,012원",
      "change": "-1원",
      "change_percent": "-0.10%",
      "signal": "중립",
      "reason": "주가가 5일 이동평균선 아래에서 횡보하며 단기 약세 흐름을 보입니다. 거래량이 적고 외국인과 기관의 매매 동향도 뚜렷하지 않아 관망이 필요합니다.",
      "capture_time": "2026-01-30 09:27:21",
      "analysis_time": "2026-01-30 09:34:23"
    },
    {
      "name": "MDS테크",
      "code": "086960",
      "current_price": "1,552원",
      "change": "+20원",
      "change_percent": "+1.31%",
      "signal": "매수",
      "reason": "주가가 5일 이동평균선을 상향 돌파하며 단기 반등 모멘텀이 강화되었습니다. 외국인과 기관의 동반 순매수세가 긍정적이며 추가 상승 여력이 있을 것으로 판단됩니다.",
      "capture_time": "2026-01-30 09:27:28",
      "analysis_time": "2026-01-30 09:34:23"
    },
    {
      "name": "원텍",
      "code": "336570",
      "current_price": "9,890원",
      "change": "+520원",
      "change_percent": "+5.54%",
      "signal": "매수",
      "reason": "금일 거래량 증가와 함께 5일 이동평균선을 상향 돌파하며 단기 상승 추세로 전환될 가능성이 높습니다. 외국인과 기관의 동반 순매수세가 긍정적입니다.",
      "capture_time": "2026-01-30 09:27:35",
      "analysis_time": "2026-01-30 09:34:23"
    },
    {
      "name": "더즌",
      "code": "462860",
      "current_price": "5,180원",
      "change": "+120원",
      "change_percent": "+2.37%",
      "signal": "중립",
      "reason": "주가가 5일 이동평균선 위에 있으나 장기 이동평균선 아래에 위치하며 방향성이 모호합니다. 외국인과 기관의 매매 동향이 혼조세라 추가적인 관망이 필요합니다.",
      "capture_time": "2026-01-30 09:27:42",
      "analysis_time": "2026-01-30 09:34:23"
    },
    {
      "name": "비엘팜텍",
      "code": "065170",
      "current_price": "2,765원",
      "change": "+635원",
      "change_percent": "+29.81%",
      "signal": "적극매수",
      "reason": "금일 대량 거래를 동반한 장대 양봉으로 모든 이동평균선을 강하게 돌파하며 강력한 상승 추세를 시작했습니다. 외국인과 기관의 강한 순매수 전환이 확인되어 강력한 매수 시그널로 판단됩니다.",
      "capture_time": "2026-01-30 09:27:49",
      "analysis_time": "2026-01-30 09:34:23"
    },
    {
      "name": "이랜시스",
      "code": "264850",
      "current_price": "8,820원",
      "change": "+150원",
      "change_percent": "+1.73%",
      "signal": "매수",
      "reason": "주가가 5일 이동평균선 위에 위치하며 단기 상승 추세를 유지하고 있습니다. 외국인과 기관의 순매수세가 긍정적이며 추가 상승 여력이 있을 것으로 판단됩니다.",
      "capture_time": "2026-01-30 09:27:56",
      "analysis_time": "2026-01-30 09:34:23"
    },
    {
      "name": "KH바텍",
      "code": "060720",
      "current_price": "18,200원",
      "change": "+1,580원",
      "change_percent": "+9.44%",
      "signal": "매수",
      "reason": "금일 대량 거래와 함께 장대 양봉이 출현하며 5일, 20일 이동평균선을 강하게 돌파했습니다. 외국인과 기관의 동반 순매수가 확인되어 추가 상승 모멘텀이 강화될 것으로 보입니다.",
      "capture_time": "2026-01-30 09:28:04",
      "analysis_time": "2026-01-30 09:34:23"
    },
    {
      "name": "하이드로리튬",
      "code": "101670",
      "current_price": "2,585원",
      "change": "+20원",
      "change_percent": "+0.78%",
      "signal": "중립",
      "reason": "주가가 5일 이동평균선 아래에서 횡보하며 약세 흐름을 보입니다. 거래량이 적고 외국인과 기관의 매매 동향도 뚜렷하지 않아 관망이 필요합니다.",
      "capture_time": "2026-01-30 09:28:11",
      "analysis_time": "2026-01-30 09:34:23"
    },
    {
      "name": "휴림에이텍",
      "code": "078590",
      "current_price": "912원",
      "change": "-34원",
      "change_percent": "-3.59%",
      "signal": "매도",
      "reason": "금일 음봉과 함께 5일 이동평균선을 하향 이탈하며 단기 하락 추세로 전환될 가능성이 높습니다. 외국인과 기관의 순매도 전환이 부정적인 신호로 판단됩니다.",
      "capture_time": "2026-01-30 09:28:18",
      "analysis_time": "2026-01-30 09:34:23"
    },
    {
      "name": "HLB",
      "code": "028300",
      "current_price": "57,500원",
      "change": "-7,800원",
      "change_percent": "-11.94%",
      "signal": "적극매도",
      "reason": "금일 급락과 함께 대량 거래가 발생하며 5일 이동평균선을 강하게 하향 이탈했습니다. 외국인과 기관의 대규모 순매도가 관찰되어 강력한 매도 시그널로 판단됩니다.",
      "capture_time": "2026-01-30 09:28:25",
      "analysis_time": "2026-01-30 09:34:23"
    },
    {
      "name": "HLB이노베이션",
      "code": "024850",
      "current_price": "2,500원",
      "change": "+190원",
      "change_percent": "+7.06%",
      "signal": "매수",
      "reason": "금일 거래량이 급증하며 5일 이동평균선을 상향 돌파하며 단기 반등 모멘텀이 강화되었습니다. 외국인의 순매수세가 긍정적이며 추가 상승 여력이 있을 것으로 판단됩니다.",
      "capture_time": "2026-01-30 09:28:33",
      "analysis_time": "2026-01-30 09:34:23"
    },
    {
      "name": "엔시트론",
      "code": "101400",
      "current_price": "499원",
      "change": "+12원",
      "change_percent": "+2.35%",
      "signal": "중립",
      "reason": "주가가 5일 이동평균선 아래에서 횡보하며 약세 흐름을 보입니다. 거래량이 적고 외국인과 기관의 매매 동향도 뚜렷하지 않아 관망이 필요합니다.",
      "capture_time": "2026-01-30 09:28:39",
      "analysis_time": "2026-01-30 09:34:23"
    },
    {
      "name": "KS인더스트리",
      "code": "101000",
      "current_price": "1,112원",
      "change": "+81원",
      "change_percent": "+7.82%",
      "signal": "매수",
      "reason": "금일 거래량이 급증하며 5일 이동평균선을 상향 돌파하며 단기 반등 모멘텀이 강화되었습니다. 외국인의 순매수세가 긍정적이며 추가 상승 여력이 있을 것으로 판단됩니다.",
      "capture_time": "2026-01-30 09:28:46",
      "analysis_time": "2026-01-30 09:34:23"
    },
    {
      "name": "한국정보인증",
      "code": "053300",
      "current_price": "6,940원",
      "change": "+170원",
      "change_percent": "+2.51%",
      "signal": "매수",
      "reason": "주가가 5일 이동평균선 위에 위치하며 단기 상승 추세를 유지하고 있습니다. 외국인과 기관의 순매수세가 긍정적이며 추가 상승 여력이 있을 것으로 판단됩니다.",
      "capture_time": "2026-01-30 09:28:53",
      "analysis_time": "2026-01-30 09:34:23"
    },
    {
      "name": "미래에셋벤처투자",
      "code": "100790",
      "current_price": "18,350원",
      "change": "+860원",
      "change_percent": "+4.90%",
      "signal": "매수",
      "reason": "금일 거래량 증가와 함께 5일 이동평균선을 상향 돌파하며 단기 상승 추세로 전환될 가능성이 높습니다. 외국인과 기관의 동반 순매수세가 긍정적입니다.",
      "capture_time": "2026-01-30 09:29:01",
      "analysis_time": "2026-01-30 09:34:23"
    },
    {
      "name": "LS머트리얼즈",
      "code": "417200",
      "current_price": "17,230원",
      "change": "+630원",
      "change_percent": "+3.80%",
      "signal": "매수",
      "reason": "금일 거래량 증가와 함께 5일 이동평균선을 상향 돌파하며 단기 상승 추세로 전환될 가능성이 높습니다. 외국인과 기관의 동반 순매수세가 긍정적입니다.",
      "capture_time": "2026-01-30 09:29:08",
      "analysis_time": "2026-01-30 09:34:23"
    },
    {
      "name": "우리로",
      "code": "046970",
      "current_price": "1,524원",
      "change": "+15원",
      "change_percent": "+0.99%",
      "signal": "중립",
      "reason": "주가가 이동평균선 아래에서 횡보하며 약세 흐름을 보입니다. 거래량이 적고 외국인과 기관의 매매 동향도 뚜렷하지 않아 관망이 필요합니다.",
      "capture_time": "2026-01-30 09:29:15",
      "analysis_time": "2026-01-30 09:34:23"
    },
    {
      "name": "알트",
      "code": "459550",
      "current_price": "4,615원",
      "change": "+10원",
      "change_percent": "+0.22%",
      "signal": "중립",
      "reason": "주가가 5일 이동평균선 아래에서 횡보하며 단기 약세 흐름을 보입니다. 외국인과 기관의 매매 동향이 혼조세로 추가적인 관망이 필요합니다.",
      "capture_time": "2026-01-30 09:29:22",
      "analysis_time": "2026-01-30 09:34:23"
    },
    {
      "name": "엑시콘",
      "code": "092870",
      "current_price": "25,000원",
      "change": "+1,500원",
      "change_percent": "+6.38%",
      "signal": "매수",
      "reason": "금일 거래량을 동반한 상승으로 5일, 20일 이동평균선을 상향 돌파하며 단기 상승 추세로 전환될 가능성이 높습니다. 외국인과 기관의 순매수 전환이 긍정적입니다.",
      "capture_time": "2026-01-30 09:29:29",
      "analysis_time": "2026-01-30 09:34:23"
    },
    {
      "name": "레이크머티리얼즈",
      "code": "281740",
      "current_price": "26,900원",
      "change": "+850원",
      "change_percent": "+3.27%",
      "signal": "매수",
      "reason": "금일 거래량을 동반한 상승으로 5일, 20일 이동평균선을 상향 돌파하며 단기 상승 추세로 전환될 가능성이 높습니다. 외국인과 기관의 순매수 전환이 긍정적입니다.",
      "capture_time": "2026-01-30 09:29:36",
      "analysis_time": "2026-01-30 09:34:23"
    },
    {
      "name": "센서뷰",
      "code": "321370",
      "current_price": "3,955원",
      "change": "+120원",
      "change_percent": "+3.13%",
      "signal": "매수",
      "reason": "금일 거래량이 급증하며 장대 양봉으로 5일 이동평균선을 상향 돌파했습니다. 외국인과 기관의 동반 순매수가 긍정적이며 단기 상승 모멘텀이 강화될 것으로 보입니다.",
      "capture_time": "2026-01-30 09:29:43",
      "analysis_time": "2026-01-30 09:34:23"
    },
    {
      "name": "나무기술",
      "code": "242040",
      "current_price": "2,385원",
      "change": "+40원",
      "change_percent": "+1.71%",
      "signal": "중립",
      "reason": "주가가 5일 이동평균선 아래에서 횡보하며 단기 약세 흐름을 보입니다. 외국인과 기관의 매매 동향이 혼조세로 추가적인 관망이 필요합니다.",
      "capture_time": "2026-01-30 09:29:50",
      "analysis_time": "2026-01-30 09:34:23"
    },
    {
      "name": "LK삼양",
      "code": "225190",
      "current_price": "1,519원",
      "change": "+40원",
      "change_percent": "+2.63%",
      "signal": "중립",
      "reason": "주가가 이동평균선 아래에서 횡보하며 약세 흐름을 보입니다. 거래량이 적고 외국인과 기관의 매매 동향도 뚜렷하지 않아 관망이 필요합니다.",
      "capture_time": "2026-01-30 09:29:57",
      "analysis_time": "2026-01-30 09:34:23"
    },
    {
      "name": "케이바이오",
      "code": "038530",
      "current_price": "266원",
      "change": "+1원",
      "change_percent": "+0.38%",
      "signal": "중립",
      "reason": "주가가 이동평균선 아래에서 횡보하며 약세 흐름을 보입니다. 거래량이 적고 외국인과 기관의 매매 동향도 뚜렷하지 않아 관망이 필요합니다.",
      "capture_time": "2026-01-30 09:30:03",
      "analysis_time": "2026-01-30 09:34:23"
    },
    {
      "name": "모비스",
      "code": "250060",
      "current_price": "5,120원",
      "change": "+120원",
      "change_percent": "+2.40%",
      "signal": "매수",
      "reason": "주가가 5일 이동평균선 위에 위치하며 단기 상승 추세를 유지하고 있습니다. 외국인과 기관의 동반 순매수세가 긍정적이며 추가 상승 여력이 있을 것으로 판단됩니다.",
      "capture_time": "2026-01-30 09:30:10",
      "analysis_time": "2026-01-30 09:34:23"
    },
    {
      "name": "루미르",
      "code": "474170",
      "current_price": "15,380원",
      "change": "+220원",
      "change_percent": "+1.45%",
      "signal": "중립",
      "reason": "주가가 5일 이동평균선 위에 있으나 장기 이동평균선 아래에 위치하며 방향성이 모호합니다. 외국인과 기관의 매매 동향이 혼조세라 추가적인 관망이 필요합니다.",
      "capture_time": "2026-01-30 09:30:18",
      "analysis_time": "2026-01-30 09:34:23"
    },
    {
      "name": "멤레이비티",
      "code": "072770",
      "current_price": "924원",
      "change": "+90원",
      "change_percent": "+10.81%",
      "signal": "매수",
      "reason": "금일 거래량이 급증하며 5일 이동평균선을 상향 돌파하며 단기 반등 모멘텀이 강화되었습니다. 외국인과 기관의 동반 순매수세가 긍정적이며 추가 상승 여력이 있을 것으로 판단됩니다.",
      "capture_time": "2026-01-30 09:30:25",
      "analysis_time": "2026-01-30 09:34:23"
    },
    {
      "name": "에코프로",
      "code": "086520",
      "current_price": "167,800원",
      "change": "-4,200원",
      "change_percent": "-2.50%",
      "signal": "매도",
      "reason": "금일 음봉과 함께 5일 이동평균선을 하향 이탈하며 단기 하락 추세로 전환될 가능성이 높습니다. 외국인과 기관의 순매도 전환이 부정적인 신호로 판단됩니다.",
      "capture_time": "2026-01-30 09:30:32",
      "analysis_time": "2026-01-30 09:34:23"
    },
    {
      "name": "협진",
      "code": "138360",
      "current_price": "2,905원",
      "change": "+140원",
      "change_percent": "+5.07%",
      "signal": "매수",
      "reason": "금일 거래량 증가와 함께 5일 이동평균선을 상향 돌파하며 단기 상승 추세로 전환될 가능성이 높습니다. 외국인과 기관의 순매수세가 긍정적입니다.",
      "capture_time": "2026-01-30 09:30:39",
      "analysis_time": "2026-01-30 09:34:23"
    },
    {
      "name": "모베이스전자",
      "code": "012860",
      "current_price": "4,190원",
      "change": "+20원",
      "change_percent": "+0.32%",
      "signal": "중립",
      "reason": "주가가 이동평균선 아래에서 횡보하며 약세 흐름을 보입니다. 거래량이 적고 외국인과 기관의 매매 동향도 뚜렷하지 않아 관망이 필요합니다.",
      "capture_time": "2026-01-30 09:30:46",
      "analysis_time": "2026-01-30 09:34:23"
    },
    {
      "name": "한컴위드",
      "code": "054920",
      "current_price": "6,350원",
      "change": "+20원",
      "change_percent": "+0.32%",
      "signal": "중립",
      "reason": "주가가 이동평균선 아래에서 횡보하며 약세 흐름을 보입니다. 거래량이 적고 외국인과 기관의 매매 동향도 뚜렷하지 않아 관망이 필요합니다.",
      "capture_time": "2026-01-30 09:30:53",
      "analysis_time": "2026-01-30 09:34:23"
    },
    {
      "name": "HLB생명과학",
      "code": "067630",
      "current_price": "4,340원",
      "change": "-25원",
      "change_percent": "-0.57%",
      "signal": "중립",
      "reason": "주가가 5일 이동평균선 아래에서 횡보하며 단기 약세 흐름을 보입니다. 외국인과 기관의 매매 동향이 혼조세로 추가적인 관망이 필요합니다.",
      "capture_time": "2026-01-30 09:31:00",
      "analysis_time": "2026-01-30 09:34:23"
    },
    {
      "name": "미투온",
      "code": "201490",
      "current_price": "4,335원",
      "change": "-25원",
      "change_percent": "-0.57%",
      "signal": "중립",
      "reason": "주가가 이동평균선 아래에서 횡보하며 약세 흐름을 보입니다. 거래량이 적고 외국인과 기관의 매매 동향도 뚜렷하지 않아 관망이 필요합니다.",
      "capture_time": "2026-01-30 09:31:07",
      "analysis_time": "2026-01-30 09:34:23"
    }
  ]
}